[
  {
    "id": 31204112,
    "title": "CFO",
    "location": "TN, Nashville",
    "experience": {
      "experience": null
    },
    "posted": {
      "date_postedStr": "9/24/2025",
      "date_posted": 1758745459000
    },
    "start": {
      "start_dateStr": null,
      "start_date": null
    },
    "end": {
      "end_dateStr": null,
      "end_date": null
    },
    "salary": null,
    "remote": 0,
    "recruiter": [
      "Shannon Philo",
      "shannon@ecastaffingsolutions.com",
      "8025781228"
    ],
    "url": "https://www1.jobdiva.com/portal/?a=hwjdnwv0hto3q9rvbesx2sp389gd230830kyhtiknlqeqp8fpl4xjho0cht0hbhy&compid=0&SearchString=#/jobs/31204112",
    "source_company": "hwjdnwv0hto3q9rvbesx2sp389gd230830kyhtiknlqeqp8fpl4xjho0cht0hbhy",
    "source_url": "https://www1.jobdiva.com/portal/?a=hwjdnwv0hto3q9rvbesx2sp389gd230830kyhtiknlqeqp8fpl4xjho0cht0hbhy&compid=0",
    "date_cutoff_days": 15
  }
]