[
  {
    "id": 31247389,
    "title": "Sr Java - AWS Programmer -Analyst",
    "location": "VA, Richmond",
    "experience": {
      "experience": null
    },
    "posted": {
      "date_postedStr": "10/1/2025",
      "date_posted": 1759342055000
    },
    "start": {
      "start_dateStr": null,
      "start_date": null
    },
    "end": {
      "end_dateStr": null,
      "end_date": null
    },
    "salary": null,
    "remote": 80,
    "recruiter": [
      "Mark Smith",
      "mark@icapsolutions.net",
      "8642364371"
    ],
    "url": "https://www1.jobdiva.com/portal/?a=cbjdnw0lxxfznplr0wz0a77kca9qq807dbe4lq2hhmpjl9udsyacdf4tx5nqvnq5&compid=0&SearchString=#/jobs/31247389",
    "source_company": "cbjdnw0lxxfznplr0wz0a77kca9qq807dbe4lq2hhmpjl9udsyacdf4tx5nqvnq5",
    "source_url": "https://www1.jobdiva.com/portal/?a=cbjdnw0lxxfznplr0wz0a77kca9qq807dbe4lq2hhmpjl9udsyacdf4tx5nqvnq5&compid=0",
    "date_cutoff_days": 15
  },
  {
    "id": 31243103,
    "title": "Solutions Architect",
    "location": "VA, Richmond",
    "experience": {
      "experience": null
    },
    "posted": {
      "date_postedStr": "10/1/2025",
      "date_posted": 1759311564000
    },
    "start": {
      "start_dateStr": null,
      "start_date": null
    },
    "end": {
      "end_dateStr": null,
      "end_date": null
    },
    "salary": null,
    "remote": 50,
    "recruiter": [
      "Lovan Shringam",
      "lovan@icapsolutions.net",
      "8642364371"
    ],
    "url": "https://www1.jobdiva.com/portal/?a=cbjdnw0lxxfznplr0wz0a77kca9qq807dbe4lq2hhmpjl9udsyacdf4tx5nqvnq5&compid=0&SearchString=#/jobs/31243103",
    "source_company": "cbjdnw0lxxfznplr0wz0a77kca9qq807dbe4lq2hhmpjl9udsyacdf4tx5nqvnq5",
    "source_url": "https://www1.jobdiva.com/portal/?a=cbjdnw0lxxfznplr0wz0a77kca9qq807dbe4lq2hhmpjl9udsyacdf4tx5nqvnq5&compid=0",
    "date_cutoff_days": 15
  },
  {
    "id": 31243098,
    "title": "System Analyst 3",
    "location": "VA, Richmond",
    "experience": {
      "experience": null
    },
    "posted": {
      "date_postedStr": "10/1/2025",
      "date_posted": 1759311447000
    },
    "start": {
      "start_dateStr": null,
      "start_date": null
    },
    "end": {
      "end_dateStr": null,
      "end_date": null
    },
    "salary": null,
    "remote": 40,
    "recruiter": [
      "Lovan Shringam",
      "lovan@icapsolutions.net",
      "8642364371"
    ],
    "url": "https://www1.jobdiva.com/portal/?a=cbjdnw0lxxfznplr0wz0a77kca9qq807dbe4lq2hhmpjl9udsyacdf4tx5nqvnq5&compid=0&SearchString=#/jobs/31243098",
    "source_company": "cbjdnw0lxxfznplr0wz0a77kca9qq807dbe4lq2hhmpjl9udsyacdf4tx5nqvnq5",
    "source_url": "https://www1.jobdiva.com/portal/?a=cbjdnw0lxxfznplr0wz0a77kca9qq807dbe4lq2hhmpjl9udsyacdf4tx5nqvnq5&compid=0",
    "date_cutoff_days": 15
  },
  {
    "id": 31241333,
    "title": "Systems Analyst 3",
    "location": "TX, Austin",
    "experience": {
      "experience": null
    },
    "posted": {
      "date_postedStr": "9/30/2025",
      "date_posted": 1759263843000
    },
    "start": {
      "start_dateStr": null,
      "start_date": null
    },
    "end": {
      "end_dateStr": null,
      "end_date": null
    },
    "salary": null,
    "remote": 40,
    "recruiter": [
      "Mark Smith",
      "mark@icapsolutions.net",
      "8642364371"
    ],
    "url": "https://www1.jobdiva.com/portal/?a=cbjdnw0lxxfznplr0wz0a77kca9qq807dbe4lq2hhmpjl9udsyacdf4tx5nqvnq5&compid=0&SearchString=#/jobs/31241333",
    "source_company": "cbjdnw0lxxfznplr0wz0a77kca9qq807dbe4lq2hhmpjl9udsyacdf4tx5nqvnq5",
    "source_url": "https://www1.jobdiva.com/portal/?a=cbjdnw0lxxfznplr0wz0a77kca9qq807dbe4lq2hhmpjl9udsyacdf4tx5nqvnq5&compid=0",
    "date_cutoff_days": 15
  },
  {
    "id": 31213568,
    "title": "Security Analyst - Consultant",
    "location": "SC, Columbia",
    "experience": {
      "experience": null
    },
    "posted": {
      "date_postedStr": "9/26/2025",
      "date_posted": 1758893925000
    },
    "start": {
      "start_dateStr": null,
      "start_date": null
    },
    "end": {
      "end_dateStr": null,
      "end_date": null
    },
    "salary": null,
    "remote": 0,
    "recruiter": [
      "Mark Smith",
      "mark@icapsolutions.net",
      "8642364371"
    ],
    "url": "https://www1.jobdiva.com/portal/?a=cbjdnw0lxxfznplr0wz0a77kca9qq807dbe4lq2hhmpjl9udsyacdf4tx5nqvnq5&compid=0&SearchString=#/jobs/31213568",
    "source_company": "cbjdnw0lxxfznplr0wz0a77kca9qq807dbe4lq2hhmpjl9udsyacdf4tx5nqvnq5",
    "source_url": "https://www1.jobdiva.com/portal/?a=cbjdnw0lxxfznplr0wz0a77kca9qq807dbe4lq2hhmpjl9udsyacdf4tx5nqvnq5&compid=0",
    "date_cutoff_days": 15
  },
  {
    "id": 31213535,
    "title": "IT Auditor 2",
    "location": "TX, Austin",
    "experience": {
      "experience": null
    },
    "posted": {
      "date_postedStr": "9/26/2025",
      "date_posted": 1758893637000
    },
    "start": {
      "start_dateStr": null,
      "start_date": null
    },
    "end": {
      "end_dateStr": null,
      "end_date": null
    },
    "salary": null,
    "remote": 50,
    "recruiter": [
      "Lovan Shringam",
      "lovan@icapsolutions.net",
      "8642364371"
    ],
    "url": "https://www1.jobdiva.com/portal/?a=cbjdnw0lxxfznplr0wz0a77kca9qq807dbe4lq2hhmpjl9udsyacdf4tx5nqvnq5&compid=0&SearchString=#/jobs/31213535",
    "source_company": "cbjdnw0lxxfznplr0wz0a77kca9qq807dbe4lq2hhmpjl9udsyacdf4tx5nqvnq5",
    "source_url": "https://www1.jobdiva.com/portal/?a=cbjdnw0lxxfznplr0wz0a77kca9qq807dbe4lq2hhmpjl9udsyacdf4tx5nqvnq5&compid=0",
    "date_cutoff_days": 15
  }
]