[
  {
    "id": 23379169,
    "title": "CSR Verification Specialist (0326)",
    "location": "IN, Indianapolis",
    "experience": {
      "experience": null
    },
    "posted": {
      "date_postedStr": "9/30/2025",
      "date_posted": 1759257060000
    },
    "start": {
      "start_dateStr": null,
      "start_date": null
    },
    "end": {
      "end_dateStr": null,
      "end_date": null
    },
    "salary": "$0-$15",
    "remote": 0,
    "recruiter": [
      "Sarah A",
      "customerservice@alpha-rae.com",
      "2604268227"
    ],
    "url": "https://www1.jobdiva.com/portal/?a=vbjdnw5ehor3o0ddlyolcn24uvtizm07e6e3cw51kalmw6ys6wkjgyvz84b4bx7k&compid=0&SearchString=#/jobs/23379169",
    "source_company": "vbjdnw5ehor3o0ddlyolcn24uvtizm07e6e3cw51kalmw6ys6wkjgyvz84b4bx7k",
    "source_url": "https://www1.jobdiva.com/portal/?a=vbjdnw5ehor3o0ddlyolcn24uvtizm07e6e3cw51kalmw6ys6wkjgyvz84b4bx7k&compid=0",
    "date_cutoff_days": 15
  },
  {
    "id": 22262278,
    "title": "CSR Verification Specialist (1118)",
    "location": "AR, Little Rock",
    "experience": {
      "experience": null
    },
    "posted": {
      "date_postedStr": "9/30/2025",
      "date_posted": 1759234860000
    },
    "start": {
      "start_dateStr": null,
      "start_date": null
    },
    "end": {
      "end_dateStr": null,
      "end_date": null
    },
    "salary": "$0-$15",
    "remote": 0,
    "recruiter": [
      "Sarah A",
      "customerservice@alpha-rae.com",
      "2604268227"
    ],
    "url": "https://www1.jobdiva.com/portal/?a=vbjdnw5ehor3o0ddlyolcn24uvtizm07e6e3cw51kalmw6ys6wkjgyvz84b4bx7k&compid=0&SearchString=#/jobs/22262278",
    "source_company": "vbjdnw5ehor3o0ddlyolcn24uvtizm07e6e3cw51kalmw6ys6wkjgyvz84b4bx7k",
    "source_url": "https://www1.jobdiva.com/portal/?a=vbjdnw5ehor3o0ddlyolcn24uvtizm07e6e3cw51kalmw6ys6wkjgyvz84b4bx7k&compid=0",
    "date_cutoff_days": 15
  },
  {
    "id": 29795230,
    "title": "REMOTE Clinical Help Desk Admin (305)",
    "location": "IN, REMOTE",
    "experience": {
      "experience": null
    },
    "posted": {
      "date_postedStr": "9/24/2025",
      "date_posted": 1758747840000
    },
    "start": {
      "start_dateStr": null,
      "start_date": null
    },
    "end": {
      "end_dateStr": null,
      "end_date": null
    },
    "salary": null,
    "remote": 0,
    "recruiter": [
      "Sarah A",
      "customerservice@alpha-rae.com",
      "2604268227"
    ],
    "url": "https://www1.jobdiva.com/portal/?a=vbjdnw5ehor3o0ddlyolcn24uvtizm07e6e3cw51kalmw6ys6wkjgyvz84b4bx7k&compid=0&SearchString=#/jobs/29795230",
    "source_company": "vbjdnw5ehor3o0ddlyolcn24uvtizm07e6e3cw51kalmw6ys6wkjgyvz84b4bx7k",
    "source_url": "https://www1.jobdiva.com/portal/?a=vbjdnw5ehor3o0ddlyolcn24uvtizm07e6e3cw51kalmw6ys6wkjgyvz84b4bx7k&compid=0",
    "date_cutoff_days": 15
  },
  {
    "id": 31186614,
    "title": "RN Case Manager – Utilization Review (Remote) ",
    "location": "IN, REMOTE",
    "experience": {
      "experience": null
    },
    "posted": {
      "date_postedStr": "9/22/2025",
      "date_posted": 1758564481000
    },
    "start": {
      "start_dateStr": null,
      "start_date": null
    },
    "end": {
      "end_dateStr": null,
      "end_date": null
    },
    "salary": null,
    "remote": 0,
    "recruiter": [
      "Sarah A",
      "customerservice@alpha-rae.com",
      "2604268227"
    ],
    "url": "https://www1.jobdiva.com/portal/?a=vbjdnw5ehor3o0ddlyolcn24uvtizm07e6e3cw51kalmw6ys6wkjgyvz84b4bx7k&compid=0&SearchString=#/jobs/31186614",
    "source_company": "vbjdnw5ehor3o0ddlyolcn24uvtizm07e6e3cw51kalmw6ys6wkjgyvz84b4bx7k",
    "source_url": "https://www1.jobdiva.com/portal/?a=vbjdnw5ehor3o0ddlyolcn24uvtizm07e6e3cw51kalmw6ys6wkjgyvz84b4bx7k&compid=0",
    "date_cutoff_days": 15
  }
]