[
  {
    "id": 31251203,
    "title": "Spotter/Helper",
    "location": "TN, Clarksville",
    "experience": {
      "experience": null
    },
    "posted": {
      "date_postedStr": "10/2/2025",
      "date_posted": 1759410000000
    },
    "start": {
      "start_dateStr": null,
      "start_date": null
    },
    "end": {
      "end_dateStr": null,
      "end_date": null
    },
    "salary": null,
    "remote": 0,
    "recruiter": [
      "Nick Lucarella",
      "nlucarella@rightech.net",
      "7323262258"
    ],
    "url": "https://www1.jobdiva.com/portal/?a=frjdnwqfozzxepksstcxg50zyoonzu05a8n7xx0glrqwa5vujtji73wai2n6mk6e&compid=0&SearchString=#/jobs/31251203",
    "source_company": "frjdnwqfozzxepksstcxg50zyoonzu05a8n7xx0glrqwa5vujtji73wai2n6mk6e",
    "source_url": "https://www1.jobdiva.com/portal/?a=frjdnwqfozzxepksstcxg50zyoonzu05a8n7xx0glrqwa5vujtji73wai2n6mk6e&compid=0",
    "date_cutoff_days": 15
  },
  {
    "id": 31249459,
    "title": "AV Installation",
    "location": "CA, Los Angeles",
    "experience": {
      "experience": null
    },
    "posted": {
      "date_postedStr": "10/1/2025",
      "date_posted": 1759353759000
    },
    "start": {
      "start_dateStr": null,
      "start_date": null
    },
    "end": {
      "end_dateStr": null,
      "end_date": null
    },
    "salary": null,
    "remote": 0,
    "recruiter": [
      "Joe Paterek",
      "joepaterek@rightech.net",
      "7325897492"
    ],
    "url": "https://www1.jobdiva.com/portal/?a=frjdnwqfozzxepksstcxg50zyoonzu05a8n7xx0glrqwa5vujtji73wai2n6mk6e&compid=0&SearchString=#/jobs/31249459",
    "source_company": "frjdnwqfozzxepksstcxg50zyoonzu05a8n7xx0glrqwa5vujtji73wai2n6mk6e",
    "source_url": "https://www1.jobdiva.com/portal/?a=frjdnwqfozzxepksstcxg50zyoonzu05a8n7xx0glrqwa5vujtji73wai2n6mk6e&compid=0",
    "date_cutoff_days": 15
  },
  {
    "id": 31242024,
    "title": "AV Installation",
    "location": "VA, Richmond",
    "experience": {
      "experience": null
    },
    "posted": {
      "date_postedStr": "9/30/2025",
      "date_posted": 1759268417000
    },
    "start": {
      "start_dateStr": null,
      "start_date": null
    },
    "end": {
      "end_dateStr": null,
      "end_date": null
    },
    "salary": null,
    "remote": 0,
    "recruiter": [
      "Joe Paterek",
      "joepaterek@rightech.net",
      "7325897492"
    ],
    "url": "https://www1.jobdiva.com/portal/?a=frjdnwqfozzxepksstcxg50zyoonzu05a8n7xx0glrqwa5vujtji73wai2n6mk6e&compid=0&SearchString=#/jobs/31242024",
    "source_company": "frjdnwqfozzxepksstcxg50zyoonzu05a8n7xx0glrqwa5vujtji73wai2n6mk6e",
    "source_url": "https://www1.jobdiva.com/portal/?a=frjdnwqfozzxepksstcxg50zyoonzu05a8n7xx0glrqwa5vujtji73wai2n6mk6e&compid=0",
    "date_cutoff_days": 15
  },
  {
    "id": 31241777,
    "title": "AV Installation",
    "location": "VA, Williamsburg",
    "experience": {
      "experience": null
    },
    "posted": {
      "date_postedStr": "9/30/2025",
      "date_posted": 1759266276000
    },
    "start": {
      "start_dateStr": null,
      "start_date": null
    },
    "end": {
      "end_dateStr": null,
      "end_date": null
    },
    "salary": null,
    "remote": 0,
    "recruiter": [
      "Joe Paterek",
      "joepaterek@rightech.net",
      "7325897492"
    ],
    "url": "https://www1.jobdiva.com/portal/?a=frjdnwqfozzxepksstcxg50zyoonzu05a8n7xx0glrqwa5vujtji73wai2n6mk6e&compid=0&SearchString=#/jobs/31241777",
    "source_company": "frjdnwqfozzxepksstcxg50zyoonzu05a8n7xx0glrqwa5vujtji73wai2n6mk6e",
    "source_url": "https://www1.jobdiva.com/portal/?a=frjdnwqfozzxepksstcxg50zyoonzu05a8n7xx0glrqwa5vujtji73wai2n6mk6e&compid=0",
    "date_cutoff_days": 15
  },
  {
    "id": 31240248,
    "title": "Spotter",
    "location": "AL, Cullman",
    "experience": {
      "experience": null
    },
    "posted": {
      "date_postedStr": "9/30/2025",
      "date_posted": 1759257905000
    },
    "start": {
      "start_dateStr": null,
      "start_date": null
    },
    "end": {
      "end_dateStr": null,
      "end_date": null
    },
    "salary": null,
    "remote": 0,
    "recruiter": [
      "Joe Candia",
      "jcandia@rightech.net",
      "7327263661"
    ],
    "url": "https://www1.jobdiva.com/portal/?a=frjdnwqfozzxepksstcxg50zyoonzu05a8n7xx0glrqwa5vujtji73wai2n6mk6e&compid=0&SearchString=#/jobs/31240248",
    "source_company": "frjdnwqfozzxepksstcxg50zyoonzu05a8n7xx0glrqwa5vujtji73wai2n6mk6e",
    "source_url": "https://www1.jobdiva.com/portal/?a=frjdnwqfozzxepksstcxg50zyoonzu05a8n7xx0glrqwa5vujtji73wai2n6mk6e&compid=0",
    "date_cutoff_days": 15
  },
  {
    "id": 31239463,
    "title": "AV Installation - Mount Pleasant WI",
    "location": "WI, Mount Pleasant",
    "experience": {
      "experience": null
    },
    "posted": {
      "date_postedStr": "9/30/2025",
      "date_posted": 1759255190000
    },
    "start": {
      "start_dateStr": null,
      "start_date": null
    },
    "end": {
      "end_dateStr": null,
      "end_date": null
    },
    "salary": null,
    "remote": 0,
    "recruiter": [
      "Joe Paterek",
      "joepaterek@rightech.net",
      "7325897492"
    ],
    "url": "https://www1.jobdiva.com/portal/?a=frjdnwqfozzxepksstcxg50zyoonzu05a8n7xx0glrqwa5vujtji73wai2n6mk6e&compid=0&SearchString=#/jobs/31239463",
    "source_company": "frjdnwqfozzxepksstcxg50zyoonzu05a8n7xx0glrqwa5vujtji73wai2n6mk6e",
    "source_url": "https://www1.jobdiva.com/portal/?a=frjdnwqfozzxepksstcxg50zyoonzu05a8n7xx0glrqwa5vujtji73wai2n6mk6e&compid=0",
    "date_cutoff_days": 15
  },
  {
    "id": 31239012,
    "title": "Cable Technician",
    "location": "TN, Nashville",
    "experience": {
      "experience": null
    },
    "posted": {
      "date_postedStr": "9/30/2025",
      "date_posted": 1759253207000
    },
    "start": {
      "start_dateStr": null,
      "start_date": null
    },
    "end": {
      "end_dateStr": null,
      "end_date": null
    },
    "salary": null,
    "remote": 0,
    "recruiter": [
      "Nick Lucarella",
      "nlucarella@rightech.net",
      "7323262258"
    ],
    "url": "https://www1.jobdiva.com/portal/?a=frjdnwqfozzxepksstcxg50zyoonzu05a8n7xx0glrqwa5vujtji73wai2n6mk6e&compid=0&SearchString=#/jobs/31239012",
    "source_company": "frjdnwqfozzxepksstcxg50zyoonzu05a8n7xx0glrqwa5vujtji73wai2n6mk6e",
    "source_url": "https://www1.jobdiva.com/portal/?a=frjdnwqfozzxepksstcxg50zyoonzu05a8n7xx0glrqwa5vujtji73wai2n6mk6e&compid=0",
    "date_cutoff_days": 15
  },
  {
    "id": 31236392,
    "title": "Cable Technician",
    "location": "MA, Wilmington",
    "experience": {
      "experience": null
    },
    "posted": {
      "date_postedStr": "9/30/2025",
      "date_posted": 1759235240000
    },
    "start": {
      "start_dateStr": null,
      "start_date": null
    },
    "end": {
      "end_dateStr": null,
      "end_date": null
    },
    "salary": null,
    "remote": 0,
    "recruiter": [
      "Nick Lucarella",
      "nlucarella@rightech.net",
      "7323262258"
    ],
    "url": "https://www1.jobdiva.com/portal/?a=frjdnwqfozzxepksstcxg50zyoonzu05a8n7xx0glrqwa5vujtji73wai2n6mk6e&compid=0&SearchString=#/jobs/31236392",
    "source_company": "frjdnwqfozzxepksstcxg50zyoonzu05a8n7xx0glrqwa5vujtji73wai2n6mk6e",
    "source_url": "https://www1.jobdiva.com/portal/?a=frjdnwqfozzxepksstcxg50zyoonzu05a8n7xx0glrqwa5vujtji73wai2n6mk6e&compid=0",
    "date_cutoff_days": 15
  },
  {
    "id": 31216203,
    "title": "Cable Technician",
    "location": "NY, Brooklyn",
    "experience": {
      "experience": null
    },
    "posted": {
      "date_postedStr": "9/26/2025",
      "date_posted": 1758912706000
    },
    "start": {
      "start_dateStr": null,
      "start_date": null
    },
    "end": {
      "end_dateStr": null,
      "end_date": null
    },
    "salary": null,
    "remote": 0,
    "recruiter": [
      "Nick Lucarella",
      "nlucarella@rightech.net",
      "7323262258"
    ],
    "url": "https://www1.jobdiva.com/portal/?a=frjdnwqfozzxepksstcxg50zyoonzu05a8n7xx0glrqwa5vujtji73wai2n6mk6e&compid=0&SearchString=#/jobs/31216203",
    "source_company": "frjdnwqfozzxepksstcxg50zyoonzu05a8n7xx0glrqwa5vujtji73wai2n6mk6e",
    "source_url": "https://www1.jobdiva.com/portal/?a=frjdnwqfozzxepksstcxg50zyoonzu05a8n7xx0glrqwa5vujtji73wai2n6mk6e&compid=0",
    "date_cutoff_days": 15
  },
  {
    "id": 31207897,
    "title": "Safety Coordinator",
    "location": "VA, Sandston",
    "experience": {
      "experience": null
    },
    "posted": {
      "date_postedStr": "9/25/2025",
      "date_posted": 1758813568000
    },
    "start": {
      "start_dateStr": null,
      "start_date": null
    },
    "end": {
      "end_dateStr": null,
      "end_date": null
    },
    "salary": null,
    "remote": 0,
    "recruiter": [
      "Michael Schiano",
      "mschiano@rightech.net",
      "7327263660"
    ],
    "url": "https://www1.jobdiva.com/portal/?a=frjdnwqfozzxepksstcxg50zyoonzu05a8n7xx0glrqwa5vujtji73wai2n6mk6e&compid=0&SearchString=#/jobs/31207897",
    "source_company": "frjdnwqfozzxepksstcxg50zyoonzu05a8n7xx0glrqwa5vujtji73wai2n6mk6e",
    "source_url": "https://www1.jobdiva.com/portal/?a=frjdnwqfozzxepksstcxg50zyoonzu05a8n7xx0glrqwa5vujtji73wai2n6mk6e&compid=0",
    "date_cutoff_days": 15
  },
  {
    "id": 31204441,
    "title": "Data Center Foreman",
    "location": "OH, Columbus",
    "experience": {
      "experience": null
    },
    "posted": {
      "date_postedStr": "9/24/2025",
      "date_posted": 1758747656000
    },
    "start": {
      "start_dateStr": null,
      "start_date": null
    },
    "end": {
      "end_dateStr": null,
      "end_date": null
    },
    "salary": null,
    "remote": 0,
    "recruiter": [
      "Michael Schiano",
      "mschiano@rightech.net",
      "7327263660"
    ],
    "url": "https://www1.jobdiva.com/portal/?a=frjdnwqfozzxepksstcxg50zyoonzu05a8n7xx0glrqwa5vujtji73wai2n6mk6e&compid=0&SearchString=#/jobs/31204441",
    "source_company": "frjdnwqfozzxepksstcxg50zyoonzu05a8n7xx0glrqwa5vujtji73wai2n6mk6e",
    "source_url": "https://www1.jobdiva.com/portal/?a=frjdnwqfozzxepksstcxg50zyoonzu05a8n7xx0glrqwa5vujtji73wai2n6mk6e&compid=0",
    "date_cutoff_days": 15
  },
  {
    "id": 31204416,
    "title": "Data Center Foreman",
    "location": "VA, Ashburn",
    "experience": {
      "experience": null
    },
    "posted": {
      "date_postedStr": "9/24/2025",
      "date_posted": 1758747555000
    },
    "start": {
      "start_dateStr": null,
      "start_date": null
    },
    "end": {
      "end_dateStr": null,
      "end_date": null
    },
    "salary": null,
    "remote": 0,
    "recruiter": [
      "Michael Schiano",
      "mschiano@rightech.net",
      "7327263660"
    ],
    "url": "https://www1.jobdiva.com/portal/?a=frjdnwqfozzxepksstcxg50zyoonzu05a8n7xx0glrqwa5vujtji73wai2n6mk6e&compid=0&SearchString=#/jobs/31204416",
    "source_company": "frjdnwqfozzxepksstcxg50zyoonzu05a8n7xx0glrqwa5vujtji73wai2n6mk6e",
    "source_url": "https://www1.jobdiva.com/portal/?a=frjdnwqfozzxepksstcxg50zyoonzu05a8n7xx0glrqwa5vujtji73wai2n6mk6e&compid=0",
    "date_cutoff_days": 15
  },
  {
    "id": 31204411,
    "title": "Data Center Foreman",
    "location": "VA, Fredericksburg",
    "experience": {
      "experience": null
    },
    "posted": {
      "date_postedStr": "9/24/2025",
      "date_posted": 1758747459000
    },
    "start": {
      "start_dateStr": null,
      "start_date": null
    },
    "end": {
      "end_dateStr": null,
      "end_date": null
    },
    "salary": null,
    "remote": 0,
    "recruiter": [
      "Michael Schiano",
      "mschiano@rightech.net",
      "7327263660"
    ],
    "url": "https://www1.jobdiva.com/portal/?a=frjdnwqfozzxepksstcxg50zyoonzu05a8n7xx0glrqwa5vujtji73wai2n6mk6e&compid=0&SearchString=#/jobs/31204411",
    "source_company": "frjdnwqfozzxepksstcxg50zyoonzu05a8n7xx0glrqwa5vujtji73wai2n6mk6e",
    "source_url": "https://www1.jobdiva.com/portal/?a=frjdnwqfozzxepksstcxg50zyoonzu05a8n7xx0glrqwa5vujtji73wai2n6mk6e&compid=0",
    "date_cutoff_days": 15
  },
  {
    "id": 31199410,
    "title": "Data Center Technician / Auditor",
    "location": "TX, Abilene",
    "experience": {
      "experience": null
    },
    "posted": {
      "date_postedStr": "9/24/2025",
      "date_posted": 1758721352000
    },
    "start": {
      "start_dateStr": null,
      "start_date": null
    },
    "end": {
      "end_dateStr": null,
      "end_date": null
    },
    "salary": null,
    "remote": 0,
    "recruiter": [
      "Michael Schiano",
      "mschiano@rightech.net",
      "7327263660"
    ],
    "url": "https://www1.jobdiva.com/portal/?a=frjdnwqfozzxepksstcxg50zyoonzu05a8n7xx0glrqwa5vujtji73wai2n6mk6e&compid=0&SearchString=#/jobs/31199410",
    "source_company": "frjdnwqfozzxepksstcxg50zyoonzu05a8n7xx0glrqwa5vujtji73wai2n6mk6e",
    "source_url": "https://www1.jobdiva.com/portal/?a=frjdnwqfozzxepksstcxg50zyoonzu05a8n7xx0glrqwa5vujtji73wai2n6mk6e&compid=0",
    "date_cutoff_days": 15
  },
  {
    "id": 31187143,
    "title": "AV Installation",
    "location": "IL, chicago",
    "experience": {
      "experience": null
    },
    "posted": {
      "date_postedStr": "9/22/2025",
      "date_posted": 1758566924000
    },
    "start": {
      "start_dateStr": null,
      "start_date": null
    },
    "end": {
      "end_dateStr": null,
      "end_date": null
    },
    "salary": null,
    "remote": 0,
    "recruiter": [
      "Joe Paterek",
      "joepaterek@rightech.net",
      "7325897492"
    ],
    "url": "https://www1.jobdiva.com/portal/?a=frjdnwqfozzxepksstcxg50zyoonzu05a8n7xx0glrqwa5vujtji73wai2n6mk6e&compid=0&SearchString=#/jobs/31187143",
    "source_company": "frjdnwqfozzxepksstcxg50zyoonzu05a8n7xx0glrqwa5vujtji73wai2n6mk6e",
    "source_url": "https://www1.jobdiva.com/portal/?a=frjdnwqfozzxepksstcxg50zyoonzu05a8n7xx0glrqwa5vujtji73wai2n6mk6e&compid=0",
    "date_cutoff_days": 15
  },
  {
    "id": 31182800,
    "title": "Data Center Technicians",
    "location": "IA, Des Moines IA",
    "experience": {
      "experience": null
    },
    "posted": {
      "date_postedStr": "9/22/2025",
      "date_posted": 1758549808000
    },
    "start": {
      "start_dateStr": null,
      "start_date": null
    },
    "end": {
      "end_dateStr": null,
      "end_date": null
    },
    "salary": null,
    "remote": 0,
    "recruiter": [
      "Joe Candia",
      "jcandia@rightech.net",
      "7327263661"
    ],
    "url": "https://www1.jobdiva.com/portal/?a=frjdnwqfozzxepksstcxg50zyoonzu05a8n7xx0glrqwa5vujtji73wai2n6mk6e&compid=0&SearchString=#/jobs/31182800",
    "source_company": "frjdnwqfozzxepksstcxg50zyoonzu05a8n7xx0glrqwa5vujtji73wai2n6mk6e",
    "source_url": "https://www1.jobdiva.com/portal/?a=frjdnwqfozzxepksstcxg50zyoonzu05a8n7xx0glrqwa5vujtji73wai2n6mk6e&compid=0",
    "date_cutoff_days": 15
  },
  {
    "id": 31175690,
    "title": "Cable Technician",
    "location": "PA, West Chester",
    "experience": {
      "experience": null
    },
    "posted": {
      "date_postedStr": "9/19/2025",
      "date_posted": 1758297560000
    },
    "start": {
      "start_dateStr": null,
      "start_date": null
    },
    "end": {
      "end_dateStr": null,
      "end_date": null
    },
    "salary": null,
    "remote": 0,
    "recruiter": [
      "Nick Lucarella",
      "nlucarella@rightech.net",
      "7323262258"
    ],
    "url": "https://www1.jobdiva.com/portal/?a=frjdnwqfozzxepksstcxg50zyoonzu05a8n7xx0glrqwa5vujtji73wai2n6mk6e&compid=0&SearchString=#/jobs/31175690",
    "source_company": "frjdnwqfozzxepksstcxg50zyoonzu05a8n7xx0glrqwa5vujtji73wai2n6mk6e",
    "source_url": "https://www1.jobdiva.com/portal/?a=frjdnwqfozzxepksstcxg50zyoonzu05a8n7xx0glrqwa5vujtji73wai2n6mk6e&compid=0",
    "date_cutoff_days": 15
  },
  {
    "id": 31175273,
    "title": "AV Technicians - Scottsdale AZ",
    "location": "AZ, Scottsdale",
    "experience": {
      "experience": null
    },
    "posted": {
      "date_postedStr": "9/19/2025",
      "date_posted": 1758294705000
    },
    "start": {
      "start_dateStr": null,
      "start_date": null
    },
    "end": {
      "end_dateStr": null,
      "end_date": null
    },
    "salary": null,
    "remote": 0,
    "recruiter": [
      "Joe Paterek",
      "joepaterek@rightech.net",
      "7325897492"
    ],
    "url": "https://www1.jobdiva.com/portal/?a=frjdnwqfozzxepksstcxg50zyoonzu05a8n7xx0glrqwa5vujtji73wai2n6mk6e&compid=0&SearchString=#/jobs/31175273",
    "source_company": "frjdnwqfozzxepksstcxg50zyoonzu05a8n7xx0glrqwa5vujtji73wai2n6mk6e",
    "source_url": "https://www1.jobdiva.com/portal/?a=frjdnwqfozzxepksstcxg50zyoonzu05a8n7xx0glrqwa5vujtji73wai2n6mk6e&compid=0",
    "date_cutoff_days": 15
  },
  {
    "id": 31174309,
    "title": "AV Technicians",
    "location": "CA, Almaeda County",
    "experience": {
      "experience": null
    },
    "posted": {
      "date_postedStr": "9/19/2025",
      "date_posted": 1758287993000
    },
    "start": {
      "start_dateStr": null,
      "start_date": null
    },
    "end": {
      "end_dateStr": null,
      "end_date": null
    },
    "salary": null,
    "remote": 0,
    "recruiter": [
      "Joe Paterek",
      "joepaterek@rightech.net",
      "7325897492"
    ],
    "url": "https://www1.jobdiva.com/portal/?a=frjdnwqfozzxepksstcxg50zyoonzu05a8n7xx0glrqwa5vujtji73wai2n6mk6e&compid=0&SearchString=#/jobs/31174309",
    "source_company": "frjdnwqfozzxepksstcxg50zyoonzu05a8n7xx0glrqwa5vujtji73wai2n6mk6e",
    "source_url": "https://www1.jobdiva.com/portal/?a=frjdnwqfozzxepksstcxg50zyoonzu05a8n7xx0glrqwa5vujtji73wai2n6mk6e&compid=0",
    "date_cutoff_days": 15
  },
  {
    "id": 31166542,
    "title": "Data Center Installer",
    "location": "IN, South Bend",
    "experience": {
      "experience": null
    },
    "posted": {
      "date_postedStr": "9/18/2025",
      "date_posted": 1758200336000
    },
    "start": {
      "start_dateStr": null,
      "start_date": null
    },
    "end": {
      "end_dateStr": null,
      "end_date": null
    },
    "salary": null,
    "remote": 0,
    "recruiter": [
      "Nick Lucarella",
      "nlucarella@rightech.net",
      "7323262258"
    ],
    "url": "https://www1.jobdiva.com/portal/?a=frjdnwqfozzxepksstcxg50zyoonzu05a8n7xx0glrqwa5vujtji73wai2n6mk6e&compid=0&SearchString=#/jobs/31166542",
    "source_company": "frjdnwqfozzxepksstcxg50zyoonzu05a8n7xx0glrqwa5vujtji73wai2n6mk6e",
    "source_url": "https://www1.jobdiva.com/portal/?a=frjdnwqfozzxepksstcxg50zyoonzu05a8n7xx0glrqwa5vujtji73wai2n6mk6e&compid=0",
    "date_cutoff_days": 15
  }
]